specbuild/__init__.py
specbuild/builder.py
specbuild/py.typed
specbuild-0.1.0.dist-info/WHEEL
specbuild-0.1.0.dist-info/METADATA
specbuild-0.1.0.dist-info/RECORD
