Metadata-Version: 2.3
Name: specbuild
Version: 0.1.0
Summary: Registry-based object builder for nested configs.
Author: Karim Abou Zeid
Author-email: Karim Abou Zeid <contact@ka.codes>
Requires-Python: >=3.10
